sparrow/__init__.py
sparrow/assistant/__init__.py
sparrow/assistant/actions.py
sparrow/assistant/review.py
sparrow/assistant/run.py
sparrow/libs/__init__.py
sparrow/libs/config.py
sparrow/libs/constants.py
sparrow/libs/html.py
sparrow/libs/llm.py
sparrow/libs/scm.py
sparrow/libs/strings.py
sparrow/main.py
sparrow/templates/code-review.html
stack_sparrow-0.0.7.dist-info/LICENSE
stack_sparrow-0.0.7.dist-info/METADATA
stack_sparrow-0.0.7.dist-info/WHEEL
stack_sparrow-0.0.7.dist-info/entry_points.txt
stack_sparrow-0.0.7.dist-info/RECORD
