Metadata-Version: 2.1
Name: stack-sparrow
Version: 0.0.7
Summary: 
Author: Akhil Ravidas
Author-email: ar@mod0.ai
Requires-Python: >=3.11,<4.0
Classifier: Programming Language :: Python :: 3
Classifier: Programming Language :: Python :: 3.11
Requires-Dist: gitpython (>=3.1.40,<4.0.0)
Requires-Dist: jinja2 (>=3.1.2,<4.0.0)
Requires-Dist: openai (>=1.1.1,<2.0.0)
Requires-Dist: pyyaml (>=6.0.1,<7.0.0)
Requires-Dist: sentry-sdk (>=1.34.0,<2.0.0)
Requires-Dist: tiktoken (>=0.5.1,<0.6.0)
Requires-Dist: typer[all] (>=0.9.0,<0.10.0)
Requires-Dist: unidiff (>=0.7.5,<0.8.0)
